stormhttp/__init__.py
stormhttp/cookies.py
stormhttp/errors.py
stormhttp/headers.py
stormhttp/message.py
stormhttp/parser.py
stormhttp/request.py
stormhttp/response.py
stormhttp/url.py
stormhttp/client/__init__.py
stormhttp/client/pool.py
stormhttp/client/session.py
stormhttp/client/cookie_jar/__init__.py
stormhttp/client/cookie_jar/abc.py
stormhttp/client/cookie_jar/jar.py
stormhttp/client/cookie_jar/storage.py
stormhttp/primitives/__init__.py
stormhttp/primitives/cookies.py
stormhttp/primitives/headers.py
stormhttp/primitives/message.py
stormhttp/primitives/parser.py
stormhttp/primitives/request.py
stormhttp/primitives/response.py
stormhttp/primitives/url.py
stormhttp/server/__init__.py
stormhttp/server/server.py
stormhttp/server/middleware/__init__.py
stormhttp/server/middleware/abc.py
stormhttp/server/middleware/cache.py
stormhttp/server/middleware/cors.py
stormhttp/server/middleware/sessions/__init__.py
stormhttp/server/middleware/sessions/middleware.py
stormhttp/server/middleware/sessions/session.py
stormhttp/server/middleware/sessions/storage/__init__.py
stormhttp/server/middleware/sessions/storage/abc.py
stormhttp/server/middleware/sessions/storage/encrypted.py
stormhttp/server/middleware/sessions/storage/fetchable.py
stormhttp/server/middleware/sessions/storage/simple.py
stormhttp/server/middleware/templating/__init__.py
stormhttp/server/middleware/templating/abc.py
stormhttp/server/middleware/templating/mako.py
stormhttp/server/websockets/__init__.py
stormhttp/server/websockets/parser.py
stormhttp/server/websockets/protocol.py
stormhttp/utils/__init__.py
stormhttp/utils/fernet.py
stormhttp-0.0.26.dist-info/DESCRIPTION.rst
stormhttp-0.0.26.dist-info/METADATA
stormhttp-0.0.26.dist-info/RECORD
stormhttp-0.0.26.dist-info/WHEEL
stormhttp-0.0.26.dist-info/metadata.json
stormhttp-0.0.26.dist-info/top_level.txt
