Metadata-Version: 2.0
Name: stormhttp
Version: 0.0.26
Summary: Lightning-fast asynchronous web framework for Python 3.5+
Home-page: https://github.com/SethMichaelLarson/stormhttp
Author: Seth Michael Larson
Author-email: sethmichaellarson@protonmail.com
License: MIT
Download-URL: https://github.com/SethMichaelLarson/stormhttp/archive/0.0.26.tar.gz
Keywords: web,async,framework
Platform: UNKNOWN
Classifier: License :: OSI Approved :: Apache Software License
Classifier: Intended Audience :: Developers
Classifier: Programming Language :: Python
Classifier: Programming Language :: Python :: 3
Classifier: Programming Language :: Python :: 3.5
Classifier: Programming Language :: Python :: 3.6
Classifier: Topic :: Internet :: WWW/HTTP
Requires-Dist: Mako (>=1.0.3)
Requires-Dist: brotlipy (>=0.5.1)
Requires-Dist: cchardet (>=1.0.0)
Requires-Dist: httptools (>=0.0.9)
Requires-Dist: pyaes (>=1.6.0)
